LICENCE-decentra_network-gui_lib__.md
LICENCE-decentra_network-lib-mix__.md
LICENCE-decentra_network-wallet-elipticcurve__.md
LICENSE-others__.md
MANIFEST.in
README.md
setup.py
decentra_network/__init__.py
decentra_network/config.py
decentra_network.egg-info/PKG-INFO
decentra_network.egg-info/SOURCES.txt
decentra_network.egg-info/dependency_links.txt
decentra_network.egg-info/entry_points.txt
decentra_network.egg-info/top_level.txt
decentra_network/accounts/account.py
decentra_network/accounts/get_accounts.py
decentra_network/accounts/get_balance.py
decentra_network/accounts/get_sequence_number.py
decentra_network/accounts/save_accounts.py
decentra_network/api/main.py
decentra_network/api/buildozer/main.py
decentra_network/apps/app_main.py
decentra_network/apps/apps_trigger.py
decentra_network/apps/remote_app.py
decentra_network/apps/testing_app/testing_app_main.py
decentra_network/blockchain/block/block_main.py
decentra_network/blockchain/block/blocks_hash.py
decentra_network/blockchain/block/change_transaction_fee.py
decentra_network/blockchain/block/create_block.py
decentra_network/blockchain/block/get_block.py
decentra_network/blockchain/block/get_block_from_blockchain_db.py
decentra_network/blockchain/block/save_block.py
decentra_network/blockchain/block/save_block_to_blockchain_db.py
decentra_network/blockchain/block/shares.py
decentra_network/blockchain/block/hash/accounts_hash.py
decentra_network/blockchain/block/hash/blocks_hash.py
decentra_network/blockchain/block/hash/calculate_hash.py
decentra_network/blockchain/block/hash/tx_hash.py
decentra_network/blockchain/candidate_block/candidate_block_main.py
decentra_network/cli/main.py
decentra_network/consensus/consensus_main.py
decentra_network/consensus/finished/finished_main.py
decentra_network/consensus/finished/transactions/transactions_main.py
decentra_network/consensus/finished/true_time/true_time_main.py
decentra_network/consensus/ongoing/ongoing_main.py
decentra_network/consensus/rounds/round_1/round_1_main.py
decentra_network/consensus/rounds/round_1/checks/checks_main.py
decentra_network/consensus/rounds/round_1/checks/candidate_blocks/candidate_blocks_main.py
