Metadata-Version: 2.1
Name: decentra-network
Version: 0.44.0
Summary: This is an open source decentralized application network. In this network, you can develop and publish decentralized applications.
Home-page: https://github.com/Decentra-Network/Decentra-Network
Author: Decentra Network Developers
Author-email: onur@decentranetwork.net
License: MPL-2.0
Keywords: python,cryptography,blockchain,p2p,python3,cryptocurrency,kivy,coin,copilot,fba,dapps,p2p-network,kivymd,blokzinciri,decentra-network,githubcopilot,blokzincir
Platform: UNKNOWN
Classifier: Development Status :: 3 - Alpha
Classifier: License :: OSI Approved :: Mozilla Public License 2.0 (MPL 2.0)
Classifier: Programming Language :: Python :: 3
Requires-Python: >=3.8
